README.md
setup.py
isc/__init__.py
isc/channel.py
isc/client.py
isc/codecs.py
isc/eventhook.py
isc/log.py
isc/server.py
isc/tests.py
isc/utils.py
isc/management/__init__.py
isc/management/commands/__init__.py
isc/management/commands/isc.py
isc/management/commands/iscinfo.py
isc/management/commands/iscshell.py
isclib.egg-info/PKG-INFO
isclib.egg-info/SOURCES.txt
isclib.egg-info/dependency_links.txt
isclib.egg-info/not-zip-safe
isclib.egg-info/requires.txt
isclib.egg-info/top_level.txt