Metadata-Version: 1.1
Name: isclib
Version: 1.1
Summary: ISC: Inter-service communication layer for Python. Compatible with gevent.
Home-page: https://github.com/and3rson/isc
Author: Andrew Dunai
Author-email: andrew@dun.ai
License: GPLv3
Keywords: rpc,python2,python3,python,gevent,amqp,pika,kombu
Platform: UNKNOWN
Classifier: Development Status :: 5 - Production/Stable
Classifier: Environment :: Web Environment
Classifier: Intended Audience :: Developers
Classifier: License :: OSI Approved :: GNU General Public License v3 (GPLv3)
Classifier: Operating System :: OS Independent
Classifier: Programming Language :: Python
